xrayradar/__init__.py
xrayradar/client.py
xrayradar/config.py
xrayradar/exceptions.py
xrayradar/models.py
xrayradar/transport.py
xrayradar/version.py
xrayradar/integrations/__init__.py
xrayradar/integrations/django.py
xrayradar/integrations/drf.py
xrayradar/integrations/fastapi.py
xrayradar/integrations/flask.py
xrayradar/integrations/graphene.py
xrayradar/integrations/logging.py
xrayradar-0.3.0.dist-info/licenses/LICENSE
xrayradar-0.3.0.dist-info/METADATA
xrayradar-0.3.0.dist-info/WHEEL
xrayradar-0.3.0.dist-info/top_level.txt
xrayradar-0.3.0.dist-info/RECORD
